README.md
setup.py
pianyuan/__init__.py
pianyuan/__main__.py
pianyuan/douban.py
pianyuan/download.py
pianyuan/find.py
pianyuan/main.py
pianyuan/mysql.py
pianyuan/package.py
pianyuan/pianyuan.py
pianyuan/shell.py
pianyuan/spider.py
pianyuan/test.py
pianyuan.egg-info/PKG-INFO
pianyuan.egg-info/SOURCES.txt
pianyuan.egg-info/dependency_links.txt
pianyuan.egg-info/entry_points.txt
pianyuan.egg-info/requires.txt
pianyuan.egg-info/top_level.txt