Metadata-Version: 2.1
Name: pianyuan
Version: 1.4.0
Summary: a spider from pianyuan.la
Home-page: https://github.com/ptrtonull-workshop/pianyuan
Author: WangTingZheng
Author-email: wangtingzheng@outlook.com
License: UNKNOWN
Platform: UNKNOWN
